{
  "main": {
    "id": "4b02735b93802676",
    "type": "split",
    "children": [
      {
        "id": "c18a15e2523da220",
        "type": "tabs",
        "children": [
          {
            "id": "f90bf5b35d913c66",
            "type": "leaf",
            "state": {
              "type": "markdown",
              "state": {
                "file": "Multimodal/LLaMA-Adapter/LLaMA-Adapter.md",
                "mode": "source",
                "source": false
              }
            }
          }
        ]
      }
    ],
    "direction": "vertical"
  },
  "left": {
    "id": "99f4564d514a9f14",
    "type": "split",
    "children": [
      {
        "id": "db3d7fdcb0aa95d2",
        "type": "tabs",
        "children": [
          {
            "id": "c283d4fa08c94d44",
            "type": "leaf",
            "state": {
              "type": "file-explorer",
              "state": {
                "sortOrder": "alphabetical"
              }
            }
          },
          {
            "id": "43ec3243428228fa",
            "type": "leaf",
            "state": {
              "type": "search",
              "state": {
                "query": "",
                "matchingCase": false,
                "explainSearch": false,
                "collapseAll": false,
                "extraContext": false,
                "sortOrder": "alphabetical"
              }
            }
          },
          {
            "id": "ea4ff9f895530a0d",
            "type": "leaf",
            "state": {
              "type": "bookmarks",
              "state": {}
            }
          },
          {
            "id": "2e4c78fdd276e293",
            "type": "leaf",
            "state": {
              "type": "graph",
              "state": {}
            }
          }
        ]
      }
    ],
    "direction": "horizontal",
    "width": 296.5
  },
  "right": {
    "id": "081c3643e733c66c",
    "type": "split",
    "children": [
      {
        "id": "7222a594ddf9c36d",
        "type": "tabs",
        "children": [
          {
            "id": "3218a44abb5a4cce",
            "type": "leaf",
            "state": {
              "type": "backlink",
              "state": {
                "file": "Multimodal/LLaMA-Adapter/LLaMA-Adapter.md",
                "collapseAll": true,
                "extraContext": false,
                "sortOrder": "alphabetical",
                "showSearch": false,
                "searchQuery": "",
                "backlinkCollapsed": false,
                "unlinkedCollapsed": true
              }
            }
          },
          {
            "id": "34158a03ae393b88",
            "type": "leaf",
            "state": {
              "type": "outgoing-link",
              "state": {
                "file": "Multimodal/LLaMA-Adapter/LLaMA-Adapter.md",
                "linksCollapsed": false,
                "unlinkedCollapsed": true
              }
            }
          },
          {
            "id": "d194ca9aa2a82fb2",
            "type": "leaf",
            "state": {
              "type": "tag",
              "state": {
                "sortOrder": "frequency",
                "useHierarchy": true
              }
            }
          },
          {
            "id": "01ceccfeb45ba8c0",
            "type": "leaf",
            "state": {
              "type": "outline",
              "state": {
                "file": "Multimodal/LLaMA-Adapter/LLaMA-Adapter.md"
              }
            }
          }
        ]
      }
    ],
    "direction": "horizontal",
    "width": 300,
    "collapsed": true
  },
  "left-ribbon": {
    "hiddenItems": {
      "switcher:Open quick switcher": false,
      "graph:Open graph view": false,
      "canvas:Create new canvas": false,
      "daily-notes:Open today's daily note": false,
      "templates:Insert template": false,
      "command-palette:Open command palette": false
    }
  },
  "active": "f90bf5b35d913c66",
  "lastOpenFiles": [
    "Multimodal/LLaMA-Adapter/LLaMA-Adapter_review.pdf",
    "Multimodal/LLaMA-Adapter/LLaMA-Adapter.md",
    "Multimodal/LLaMA-Adapter/LLaMA-Adapter.pdf",
    "source/llama_adpter/table3_4.png",
    "source/llama_adpter/table2.png",
    "source/llama_adpter/figure4.png",
    "source/llama_adpter/figure5.png",
    "source/llama_adpter/figure6.png",
    "source/llama_adpter/table1.png",
    "source/llama_adpter/figure3.png",
    "source/llama_adpter/figure2.png",
    "source/llama_adpter/figure1.png",
    "source/llama_adpter",
    "source/원앙",
    "Multimodal/BLIP2/BLIP2.md",
    "Multimodal/BLIP2/BLIP2.pdf",
    "source/BLIP2/table1.png",
    "source/BLIP2",
    "source/새 폴더",
    "Multimodal/BLIP/BLIP.md",
    "Multimodal/BLIP/BLIP.pdf",
    "2019/2019.11. Momentum Contrast for Unsupervised Visual Representation Learning.pdf",
    "2020/2019.11. Momentum Contrast for Unsupervised Visual Representation Learning.pdf",
    "Diffusion/2022. High-Resolution Image Synthesis with Latent Diffusion Models/High-Resolution Image Synthesis with Latent Diffusion Models.md",
    "Multimodal/FILIP/FILIP.md",
    "Multimodal/DeCLIP/DeCLIP.md",
    "Multimodal/CLIP/CLIP.md",
    "2021/2021.6 ViT/ViT.md",
    "Review.md",
    "graph/MultiModal.md",
    "Zero-shot Transfer.md",
    "[.md",
    "graph/Vision.md",
    "2018/2018.10 BERT/BERT.md",
    "graph/NLP.md",
    "Pasted image 20240413073238.png.md",
    "CLIP - Learning Transferable Visual Models From Natural Language Supervision. ICML'2021..md",
    "2017/2017.04. Attention is All You Need/Attention is All You Need.md",
    "2017/2017.04. Attention All You Need/무제 파일.canvas",
    "NLP/무제 파일.md"
  ]
}